terminal_robot/__init__.py
terminal_robot/main.py
terminal_robot/robotspeech.py
terminal_robot/images/robot_e.png
terminal_robot/images/robot_h.png
terminal_robot/images/robot_m.png
terminal_robot/images/robot_o.png
terminal_robot/images/robot_s.png
terminal_robot/images/robot_u.png
terminal_robot-1.0.0.dist-info/METADATA
terminal_robot-1.0.0.dist-info/WHEEL
terminal_robot-1.0.0.dist-info/entry_points.txt
terminal_robot-1.0.0.dist-info/RECORD
