Metadata-Version: 2.3
Name: terminal-robot
Version: 1.0.0
Summary: A fun cool speaking robot right in your terminal.
Requires-Python: >=3.12
Requires-Dist: click>=8.1.7
Requires-Dist: metaphone>=0.6
Requires-Dist: multithreading>=0.2.0
Requires-Dist: opencv-python>=4.10.0.84
Requires-Dist: thread>=2.0.5
